pffmpeg/__init__.py
pffmpeg/__main__.py
pffmpeg/_args.py
pffmpeg/_cli.py
pffmpeg/_runner.py
pffmpeg/_utils.py
pffmpeg-1.0.1.dist-info/METADATA
pffmpeg-1.0.1.dist-info/WHEEL
pffmpeg-1.0.1.dist-info/entry_points.txt
pffmpeg-1.0.1.dist-info/licenses/LICENSE
pffmpeg-1.0.1.dist-info/RECORD
