Metadata-Version: 2.4
Name: pffmpeg
Version: 1.0.1
Summary: Progress bar for FFmpeg
Project-URL: Homepage, https://pypi.org/project/pffmpeg/
Project-URL: Documentation, https://cguichard.github.io/pffmpeg/
Project-URL: Changelog, https://cguichard.github.io/pffmpeg/changelog/
Project-URL: Source, https://github.com/CGuichard/pffmpeg
Project-URL: Tracker, https://github.com/CGuichard/pffmpeg/issues
Author-email: Clément GUICHARD <clement.guichard0@gmail.com>
License-Expression: MIT
License-File: LICENSE
Keywords: ffmpeg,progress,rich
Classifier: Development Status :: 5 - Production/Stable
Classifier: Environment :: Console
Classifier: Framework :: Hatch
Classifier: Framework :: MkDocs
Classifier: Framework :: Pytest
Classifier: Framework :: tox
Classifier: License :: OSI Approved :: MIT License
Classifier: Natural Language :: English
Classifier: Operating System :: OS Independent
Classifier: Programming Language :: Python
Classifier: Programming Language :: Python :: 3
Classifier: Programming Language :: Python :: 3 :: Only
Classifier: Programming Language :: Python :: 3.10
Classifier: Programming Language :: Python :: 3.11
Classifier: Programming Language :: Python :: 3.12
Classifier: Programming Language :: Python :: 3.13
Classifier: Programming Language :: Python :: 3.14
Classifier: Programming Language :: Python :: Implementation :: CPython
Classifier: Topic :: Multimedia
Classifier: Topic :: Multimedia :: Video
Classifier: Topic :: Multimedia :: Video :: Conversion
Classifier: Topic :: Software Development :: Version Control :: Git
Classifier: Topic :: Utilities
Classifier: Typing :: Typed
Requires-Python: >=3.10
Requires-Dist: rich~=14.3
